{"8mnzSJcEw+0SHiYg5PwhDw==":"logo%20(1)-121x24.png","GQLpgtz1Yta50wAOpjl16w==":"salon01-1920x1080.jpeg","rYFhxR8dzKTOGhybYC3rzQ==":"mebelbos-240x172.jpg","Ih71vMluzVso7nbE0NGWcw==":"halmarlogo-225x225.png","2Q6oifE4lv1ZmXvO9jwfvQ==":"stolkar-240x150.png","J384IpeIjT+SYISJUSrTuw==":"mlmeble-logo-1-240x240.jpg","eVZE9vwWIgf7wTDTDphGqQ==":"jarstol-224x225.png","PRm5q9ulY38DfujJGdx4yg==":"mlot1111-149x208.png","lyJ2vVEfSQXVLmm0RySvIQ==":"pobrane-240x131.png","jPihFDutlmom/TB/gB+6vg==":"ewafffff-200x150.jpg","70KuITQ5ECNdXiBvXYWDtQ==":"aabbcc-1824x1368.jpeg","YTAHU/oS0lPTPGuWeRjGvg==":"4-1050x600.png","TDoMEBdLLApRHRfDGYTnog==":"projekt%20bez%20tytu%C5%82u%20(16)-1920x1080.png","tRewQXCGIngbErhY8mUpZw==":"logoczrn%20(1)-613x120.png","hkl283iuwPenuN1mzvO/cA==":"logo%20(1)-621x122.png","O5u6SUYCxj05OInAOCsMuw==":"dsc-354-1288x725.jpg","jgNxBR4svdSsGv8vDHS2iw==":"img_20190510-133050-1288x1288.jpg","cbiX7q99qYjcmj5b9Zuatw==":"img_20190515-143439-1288x1288.jpg","OMV28UtKSrniGq67GFRWSw==":"img_20190531-133044-1288x1717.jpg","y/BH9XAIZH+MrOesj2rOEw==":"img_20200701_121831_resized_20200701-123308873-1288x1717.jpg","QqeNduAgEvwyKsglh645Hg==":"img_20200701_121729_resized_20200701-123312368-1288x1717.jpg","kjKgSeUFBk1W1ejn9yed4A==":"img_20200320_112652_resized_20200320-24137798-1288x966.jpg","AY7wVub/q06y7obuAtVo6A==":"img_20200910_124810_resized_20200911-121905695-1288x1717.jpg","4tQhUiCsaWqmi9bglnIBug==":"img_20200910_154819_resized_20200911-121903476-1288x966.jpg","a4KAFnkm12NP+ud3fEkR2A==":"img_20200910_154808_resized_20200911-121903833-1288x1717.jpg","4YtVIazPo1jF9FsrBVZ14w==":"img_20200910_124848_resized_20200911-121904770-1288x1717.jpg","np/F1DgKKSVXyXjprWJb2w==":"img_20200910_124642_resized_20200911-121906600-1288x966.jpg","+bgZb/6whielY0c6OEQOrQ==":"img_20200910_124839_resized_20200911-121904469-1256x1675.jpg","8AZxnBoQuvhw4vrVumHRlA==":"img_20191218_184834_resized_20191219-83001308-1900x1425.jpg","TwEMAyH2VaS8b+n5vlItZA==":"img_20191218_184848_resized_20191219-82958827-1900x2533.jpg","BvufiG2CfNF6o9hyzMcZAQ==":"img_20191218_184839_resized_20191219-83003496-1900x2533.jpg","DN1HrQwqrUeY+tjyF/j+Dw==":"img_20191218_184834_resized_20191219-83001308-1476x1107.jpg","l5OlQmAbakunCcIFuLvTJg==":"projekt%20bez%20tytu%C5%82u%20(19)-1920x1080.png","KJRNGWjMkf+JYb8QRZ5f/w==":"projekt%20bez%20tytu%C5%82u%20(20)-1920x1080.png","z84kMOTKEOWcNZoOuS5Csw==":"projekt%20bez%20tytu%C5%82u%20(21)-1920x1080.png","LX2ONODHEVKip1YZs9MaXw==":"20230121-100859-1256x707.jpg","fdkg1noShyu/u09EjaECxQ==":"20230121-100859-1900x1069.jpg","Q3xp5aVbuIAHuc3VdnfHzw==":"20230121-100906-1900x1069.jpg","ehFJ1uP2phGhATnmI+ck2A==":"20230121-100919-1900x1069.jpg","Zwu2LtNnRGt+yfMG0d9aHQ==":"20230121-100909-1900x1069.jpg","C8rQgZog8V+bDR1wsbdqAw==":"ikona%201-82x78.png","Vb7O0FFDUSs2cK1XnZ2RWA==":"ikona%202-83x92.png","bD6e1VVuyB5qLHT8pdjkgg==":"img_20190515-143504-1256x1256.jpg","d5Ok7zC/xP6tubHsBWjj6Q==":"img_20190510-133050-1256x1256.jpg","qUWGodtjQSWWtps7+r7FKw==":"img_20190515-143439-1256x1256.jpg","wvIU7KyXs7QAk/0pdrcRSA==":"projekt%20bez%20tytu%C5%82u%20(28)-500x500.png","VsCHTZhcdOz1O6G/NRNL9A==":"projekt%20bez%20tytu%C5%82u%20(27)-500x500.png","RT/bx5R0IDAeNFHEv+l/Xw==":"projekt%20bez%20tytu%C5%82u%20(26)-500x500.png","/p81ZlIZgH6UgIxNmPDX4g==":"projekt%20bez%20tytu%C5%82u%20(25)-500x500.png","HwNmkmB//pzGiPwQr/j2yw==":"glazura%20kr%C3%B3lewska%20(15)-1288x725.png","B29ExuWIewCuZ+UWmSEQ+A==":"projekt%20bez%20tytu%C5%82u%20(32)-500x500.png","qBIWa3zNhkOLY5vlgygQfQ==":"projekt%20bez%20tytu%C5%82u%20(31)-500x500.png","Gfs4Q57OI/yz/gnYOwB3Hw==":"projekt%20bez%20tytu%C5%82u%20(30)-500x500.png","02dnEAPolb07WxxdqMiB6g==":"projekt%20bez%20tytu%C5%82u%20(29)-500x500.png","4aCL3Eksf3JNpN0Kj9y8hw==":"ca-2000x566.jpg","ZYlrpjMGFbKzEMGOb6QM+g==":"m%20(2)-100x100.png","2N1F5chAH8+LijikSRnvFA==":"projekt%20bez%20tytu%C5%82u%20(33)-1920x1080.png"}